{
  "session_id": "critic_20250818_202239",
  "timestamp": "2025-08-18T20:22:39.562018",
  "total_findings": 5,
  "severity_breakdown": {
    "HIGH": 3,
    "MEDIUM": 2,
    "LOW": 0
  },
  "immediate_actions": [
    "Formalisation mathématique des concepts",
    "Prototypes Python pour validation",
    "Protocole expérimental rigoureux"
  ],
  "medium_term_actions": [
    "Rattrapage littérature 2020-2025",
    "Étude marché et cas d'usage concrets"
  ],
  "long_term_actions": [],
  "detailed_findings": [
    {
      "category": "theoretical_foundations",
      "severity": "HIGH",
      "component": "Base conceptuelle",
      "issue": "Concepts sémantiques insuffisamment formalisés",
      "impact": "Manque de rigueur scientifique",
      "counter_argument": "Innovation nécessite exploration conceptuelle",
      "improvement_suggestion": "Formalisation mathématique des concepts",
      "confidence": 0.8
    },
    {
      "category": "theoretical_foundations",
      "severity": "MEDIUM",
      "component": "Références académiques",
      "issue": "Bibliographie incomplète en linguistique moderne",
      "impact": "Isolation du courant scientifique principal",
      "counter_argument": "Focus sur innovation plutôt que conformité",
      "improvement_suggestion": "Rattrapage littérature 2020-2025",
      "confidence": 0.9
    },
    {
      "category": "technical_implementation",
      "severity": "HIGH",
      "component": "Architecture Rust",
      "issue": "Complexité excessive pour cas d'usage initial",
      "impact": "Barrière adoption développeurs",
      "counter_argument": "Rust garantit sécurité mémoire",
      "improvement_suggestion": "Prototypes Python pour validation",
      "confidence": 0.7
    },
    {
      "category": "scientific_validation",
      "severity": "HIGH",
      "component": "Tests empiriques",
      "issue": "Absence de validation expérimentale",
      "impact": "Hypothèses non vérifiées",
      "counter_argument": "Phase conceptuelle nécessaire avant tests",
      "improvement_suggestion": "Protocole expérimental rigoureux",
      "confidence": 0.95
    },
    {
      "category": "commercial_viability",
      "severity": "MEDIUM",
      "component": "Marché cible",
      "issue": "Marché non identifié clairement",
      "impact": "Adoption commerciale incertaine",
      "counter_argument": "Innovation crée nouveaux marchés",
      "improvement_suggestion": "Étude marché et cas d'usage concrets",
      "confidence": 0.7
    }
  ]
}